data_processing/__init__.py
data_processing/numeric_ops.py
data_processing/stats.py
data_processing/text_cleaner.py
data_processing_rxy-1.0.0.dist-info/METADATA
data_processing_rxy-1.0.0.dist-info/WHEEL
data_processing_rxy-1.0.0.dist-info/top_level.txt
data_processing_rxy-1.0.0.dist-info/RECORD
