Metadata-Version: 2.4
Name: data_processing_rxy
Version: 1.0.0
Summary: A data processing library with numeric, text, and stats tools
Author: Your Name
Author-email: your@email.com
Requires-Python: >=3.8
Requires-Dist: numpy>=1.21.0
Dynamic: author
Dynamic: author-email
Dynamic: description
Dynamic: description-content-type
Dynamic: requires-dist
Dynamic: requires-python
Dynamic: summary
